QLed.py
QLed-1.3.dist-info/DESCRIPTION.rst
QLed-1.3.dist-info/METADATA
QLed-1.3.dist-info/RECORD
QLed-1.3.dist-info/WHEEL
QLed-1.3.dist-info/metadata.json
QLed-1.3.dist-info/top_level.txt
